{
    "IsDebug" : true,
    "port" : "8080",
    "jwtSecret" : "rity",
    "clientLocation" : "http://localhost:8381",
    "sqlServer" : {
        "host": "code4ro..rds.amazonaws.com",
        "port": "3306",
        "dialect": "mysql",
        "dialectOptions": {
            "charset": "utf8"
        }
    },
    "sqlLogin" : {
        "username": "sa",
        "password" : "8",
        "database" : "cq"
    },
    "S3" : {
        "access-key" : "",
        "secret-key" : "",
        "bucket-url-root" : "",
        "bucket-app-folder" : ""
    }
}
